lamin_utils/__init__.py
lamin_utils/_base62.py
lamin_utils/_colors.py
lamin_utils/_compat.py
lamin_utils/_inspect.py
lamin_utils/_logger.py
lamin_utils/_lookup.py
lamin_utils/_map_synonyms.py
lamin_utils/_python_version.py
lamin_utils/_search.py
lamin_utils/_standardize.py
lamin_utils-0.16.3.dist-info/licenses/LICENSE
lamin_utils-0.16.3.dist-info/WHEEL
lamin_utils-0.16.3.dist-info/METADATA
lamin_utils-0.16.3.dist-info/RECORD
